adbpg_mcp_server_test.py
adbpg_mcp_server_test-0.1.8.dist-info/METADATA
adbpg_mcp_server_test-0.1.8.dist-info/WHEEL
adbpg_mcp_server_test-0.1.8.dist-info/entry_points.txt
adbpg_mcp_server_test-0.1.8.dist-info/licenses/LICENSE
adbpg_mcp_server_test-0.1.8.dist-info/RECORD
