Metadata-Version: 2.4
Name: adbpg-mcp-server-test
Version: 0.1.8
Summary: MCP server for AnalyticDB PostgreSQL
License-File: LICENSE
Requires-Python: >=3.10
Requires-Dist: mcp>=1.4.0
Requires-Dist: psycopg>=3.1.0
Requires-Dist: pydantic>=2.0.0
Requires-Dist: python-dotenv>=1.0.0
